certbot_dns_hover/HoverClient.py
certbot_dns_hover/__init__.py
certbot_dns_hover/dns_hover.py
certbot_dns_hover/dns_hover_test.py
certbot_dns_hover-1.2.4.dist-info/LICENSE.txt
certbot_dns_hover-1.2.4.dist-info/METADATA
certbot_dns_hover-1.2.4.dist-info/WHEEL
certbot_dns_hover-1.2.4.dist-info/entry_points.txt
certbot_dns_hover-1.2.4.dist-info/top_level.txt
certbot_dns_hover-1.2.4.dist-info/RECORD
